libweb/__init__.py
libweb/dns.py
libweb/http.py
libweb/json.py
libweb/regex.py
libweb/xpath.py
libweb-1.0.0.dist-info/DESCRIPTION.rst
libweb-1.0.0.dist-info/METADATA
libweb-1.0.0.dist-info/RECORD
libweb-1.0.0.dist-info/WHEEL
libweb-1.0.0.dist-info/metadata.json
libweb-1.0.0.dist-info/top_level.txt
