Metadata-Version: 2.0
Name: libweb
Version: 1.0.0
Summary: Python Web Service Parsing Library
Home-page: http://hurricanelabs.github.io/libweb/
Author: Steve McMaster
Author-email: mcmaster@hurricanelabs.com
License: UNKNOWN
Platform: UNKNOWN
Classifier: License :: OSI Approved :: MIT License
Classifier: Programming Language :: Python :: 3 :: Only
Classifier: Development Status :: 4 - Beta
Requires-Dist: defusedxml
Requires-Dist: dnspython3
Requires-Dist: filemagic
Requires-Dist: html5lib
Requires-Dist: jsonpath-rw-ext
Requires-Dist: lxml
Requires-Dist: relatime
Requires-Dist: requests
Requires-Dist: tzlocal
